{
    "Version": null,
    "Sections": [
        {
            "Name": "GeneralSettings",
            "Description": null,
            "IsAdvanced": false,
            "Keys": [
                {
                    "Value": true,
                    "Name": "ForceCompassGeneration",
                    "Description": null,
                    "$version": "v1",
                    "$type": "DaggerfallWorkshop.Game.Utility.ModSupport.ModSettings.ToggleKey"
                }
            ],
            "$version": "v1"
        },
        {
            "Name": "CompassKeys",
            "Description": "Setup smart control keys",
            "IsAdvanced": false,
            "Keys": [
                {
                    "Value": "KeypadPlus",
                    "Name": "ZoomIn:FullViewCompass",
                    "Description": "Hold to zoom in; double tap for full view.",
                    "$version": "v1",
                    "$type": "DaggerfallWorkshop.Game.Utility.ModSupport.ModSettings.TextKey"
                },
                {
                    "Value": "KeypadMinus",
                    "Name": "ZoomOut:SettingScroll",
                    "Description": "Hold to zoom out; double tap for setting scroll.",
                    "$version": "v1",
                    "$type": "DaggerfallWorkshop.Game.Utility.ModSupport.ModSettings.TextKey"
                },
                {
                    "Value": "P",
                    "Name": "ToggleIconFrustrum:ToggleEffects",
                    "Description": "Tap once to toggle Frustrum Calling; double tap to toggle effects on/off.",
                    "$version": "v1",
                    "$type": "DaggerfallWorkshop.Game.Utility.ModSupport.ModSettings.TextKey"
                }
            ],
            "$version": "v1"
        },
        {
            "Name": "CompassGraphicsSettings",
            "Description": "Setup what the compass appears, including what effects appear.",
            "IsAdvanced": true,
            "Keys": [
                {
                    "Value": true,
                    "Name": "EquippableCompass",
                    "Description": "Do you want the compass to be an item that must be equipped to use?",
                    "$version": "v1",
                    "$type": "DaggerfallWorkshop.Game.Utility.ModSupport.ModSettings.ToggleKey"
                },
                {
                    "Value": true,
                    "Name": "EnableBloodEffect",
                    "Description": "Blood covers compass when taking damage to your chest. Armor/clothing reduce this damage. Rain cleans it.",
                    "$version": "v1",
                    "$type": "DaggerfallWorkshop.Game.Utility.ModSupport.ModSettings.ToggleKey"
                },
                {
                    "Value": true,
                    "Name": "CompassBackgroundImageEnabled",
                    "Description": "Does the compass background show endless dwemer gears or your choosen color?",
                    "$version": "v1",
                    "$type": "DaggerfallWorkshop.Game.Utility.ModSupport.ModSettings.ToggleKey"
                },
                {
                    "Options": [
                        "Red",
                        "Green",
                        "Blue",
                        "Orange",
                        "Purple",
                        "Yellow",
                        "White",
                        "Black"
                    ],
                    "Value": 6,
                    "Name": "CompassBackgroundColor",
                    "Description": "What color is the compass background? If you want default gear colors, set to color white.",
                    "$version": "v1",
                    "$type": "DaggerfallWorkshop.Game.Utility.ModSupport.ModSettings.MultipleChoiceKey"
                },
                {
                    "Min": 0.0,
                    "Max": 1.0,
                    "Value": 0.4,
                    "Name": "CompassBackgroundBrightness",
                    "Description": "How bright do you want the background color/texture? Defaults to 50% so overlay is still easy to see.",
                    "$version": "v1",
                    "$type": "DaggerfallWorkshop.Game.Utility.ModSupport.ModSettings.SliderFloatKey"
                },
                {
                    "Min": 0.0,
                    "Max": 1.0,
                    "Value": 1.0,
                    "Name": "CompassBackgroundTransperency",
                    "Description": "How transperent do you want the color/image of the compass background to be?",
                    "$version": "v1",
                    "$type": "DaggerfallWorkshop.Game.Utility.ModSupport.ModSettings.SliderFloatKey"
                },
                {
                    "Value": true,
                    "Name": "EnableDamageEffect",
                    "Description": "The glass will fracture and then break the more damage the compass takes. This creates a repair kit and items to repair damage.",
                    "$version": "v1",
                    "$type": "DaggerfallWorkshop.Game.Utility.ModSupport.ModSettings.ToggleKey"
                },
                {
                    "Value": true,
                    "Name": "EnableWaterDropEffect",
                    "Description": "When raining or swimming, water droplets hit your compass and slide down it. Disabling this does not disable rain cleaning effect.",
                    "$version": "v1",
                    "$type": "DaggerfallWorkshop.Game.Utility.ModSupport.ModSettings.ToggleKey"
                },
                {
                    "Value": true,
                    "Name": "EnableMudEffect",
                    "Description": "Mud collects on your compass based on how much you move, the season, the region, the weather, and the climate. Rain cleans it.",
                    "$version": "v1",
                    "$type": "DaggerfallWorkshop.Game.Utility.ModSupport.ModSettings.ToggleKey"
                },
                {
                    "Value": true,
                    "Name": "EnableDirtEffect",
                    "Description": "Dirt will collect on your compass based on how much you move, the season, the region, the weather, and the climate. Rain cleans it.",
                    "$version": "v1",
                    "$type": "DaggerfallWorkshop.Game.Utility.ModSupport.ModSettings.ToggleKey"
                },
                {
                    "Value": true,
                    "Name": "EnableDustEffect",
                    "Description": "Dust will collect on your compass based on how much you move, the season, the region, the weather, and the climate. Rain cleans it.",
                    "$version": "v1",
                    "$type": "DaggerfallWorkshop.Game.Utility.ModSupport.ModSettings.ToggleKey"
                },
                {
                    "Value": true,
                    "Name": "EnableFrostEffect",
                    "Description": "Frost will grow based on the season, the region, the weather, and the climate. Rain cleans it. Going inside fades it away.",
                    "$version": "v1",
                    "$type": "DaggerfallWorkshop.Game.Utility.ModSupport.ModSettings.ToggleKey"
                },
                {
                    "Value": true,
                    "Name": "EnableMagicTearEffect",
                    "Description": "Magical tears will appear when your grass breaks open. The more glass lost, the more magic tries to escape causing tears.",
                    "$version": "v1",
                    "$type": "DaggerfallWorkshop.Game.Utility.ModSupport.ModSettings.ToggleKey"
                },
                {
                    "Min": 1,
                    "Max": 10,
                    "Value": 2,
                    "Name": "FrameUpdateIntervals",
                    "Description": "What frame interval at 60 fps should the effects update. Higher numbers = better performance, but the choppier effect is.",
                    "$version": "v1",
                    "$type": "DaggerfallWorkshop.Game.Utility.ModSupport.ModSettings.SliderIntKey"
                },
                {
                    "Value": false,
                    "Name": "RealisticViewMap",
                    "Description": null,
                    "$version": "v1",
                    "$type": "DaggerfallWorkshop.Game.Utility.ModSupport.ModSettings.ToggleKey"
                }
            ],
            "$version": "v1"
        },
        {
            "Name": "CompassEffectSettings",
            "Description": "Setup how the effects operate in game..",
            "IsAdvanced": true,
            "Keys": [
                {
                    "Min": 0.0,
                    "Max": 1.0,
                    "Value": 0.2,
                    "Name": "GlassTransperency",
                    "Description": "How frosted do you want the glass? lower values the clearer the glass.",
                    "$version": "v1",
                    "$type": "DaggerfallWorkshop.Game.Utility.ModSupport.ModSettings.SliderFloatKey"
                },
                {
                    "Min": 0.0,
                    "Max": 600.0,
                    "Value": 300.0,
                    "Name": "FrostFadeIn",
                    "Description": "How many seconds for the frost effect to fully appear? Seasons, climate, & weather affect this.",
                    "$version": "v1",
                    "$type": "DaggerfallWorkshop.Game.Utility.ModSupport.ModSettings.SliderFloatKey"
                },
                {
                    "Min": 0.0,
                    "Max": 600.0,
                    "Value": 60.0,
                    "Name": "MudLoopTimer",
                    "Description": "How many seconds until a chance for mud on your compass? Seasons, climates & weather affect this.",
                    "$version": "v1",
                    "$type": "DaggerfallWorkshop.Game.Utility.ModSupport.ModSettings.SliderFloatKey"
                },
                {
                    "Min": 0.0,
                    "Max": 600.0,
                    "Value": 5.0,
                    "Name": "DirtLoopTimer",
                    "Description": "How many seconds for random dirt check on your compass? Seasons, climates, & weather affect this.",
                    "$version": "v1",
                    "$type": "DaggerfallWorkshop.Game.Utility.ModSupport.ModSettings.SliderFloatKey"
                },
                {
                    "Min": 0.0,
                    "Max": 1800.0,
                    "Value": 600.0,
                    "Name": "DustFadeIn",
                    "Description": "How many seconds for dust effect to fully appear? Seasons, regaions, & weather affect this.",
                    "$version": "v1",
                    "$type": "DaggerfallWorkshop.Game.Utility.ModSupport.ModSettings.SliderFloatKey"
                },
                {
                    "Min": 0.0,
                    "Max": 100.0,
                    "Value": 6.0,
                    "Name": "MaxBloodDamageTrigger",
                    "Description": "What percentage of health lose before the blood effect does a random check? Random check is (this number * .25f) to this number.",
                    "$version": "v1",
                    "$type": "DaggerfallWorkshop.Game.Utility.ModSupport.ModSettings.SliderFloatKey"
                },
                {
                    "Min": 0,
                    "Max": 100,
                    "Value": 30,
                    "Name": "MaxRainDrops",
                    "Description": "How many droplets appear on the compass at a time. More droplets cost more fps. Turn this down if having low fps issues.",
                    "$version": "v1",
                    "$type": "DaggerfallWorkshop.Game.Utility.ModSupport.ModSettings.SliderIntKey"
                },
                {
                    "Min": 0,
                    "Max": 120,
                    "Value": 20,
                    "Name": "WaterDropletInterval",
                    "Description": "How quickly or slowly will droplets appear on compass. Lower the number the faster they will appear randomly.",
                    "$version": "v1",
                    "$type": "DaggerfallWorkshop.Game.Utility.ModSupport.ModSettings.SliderIntKey"
                },
                {
                    "Min": 0.2,
                    "Max": 2.0,
                    "Value": 0.2,
                    "Name": "NpcCellUpdateInterval",
                    "Description": "How often do you want a cell scanned for new npcs to add markers too. Lower the time, the higher the cpu demand.",
                    "$version": "v1",
                    "$type": "DaggerfallWorkshop.Game.Utility.ModSupport.ModSettings.SliderFloatKey"
                },
                {
                    "Min": 0.0,
                    "Max": 1.0,
                    "Value": 0.3,
                    "Name": "NpcMarkerUpdateInterval",
                    "Description": "How often should npc markers be checked for detection? Higher numbers = less demand but slower marker detection.",
                    "$version": "v1",
                    "$type": "DaggerfallWorkshop.Game.Utility.ModSupport.ModSettings.SliderFloatKey"
                },
                {
                    "Min": 0,
                    "Max": 500,
                    "Value": 100,
                    "Name": "BuildingIconSpawnTime",
                    "Description": "How long for building icons to appear. The longer it takes, the less fps stalls on town creations. 1 second default.",
                    "$version": "v1",
                    "$type": "DaggerfallWorkshop.Game.Utility.ModSupport.ModSettings.SliderIntKey"
                },
                {
                    "Value": false,
                    "Name": "IconFrustrumCalling",
                    "Description": "Building icons are only enabled/rendered when in camera view. Only recommended for high cpu/low gpu comps.",
                    "$version": "v1",
                    "$type": "DaggerfallWorkshop.Game.Utility.ModSupport.ModSettings.ToggleKey"
                },
                {
                    "Min": 0,
                    "Max": 200,
                    "Value": 80,
                    "Name": "SmartViewTriggerDistance",
                    "Description": "How far away zoom is before smart view settings flips building labels to icons?",
                    "$version": "v1",
                    "$type": "DaggerfallWorkshop.Game.Utility.ModSupport.ModSettings.SliderIntKey"
                }
            ],
            "$version": "v1"
        }
    ]
}